i2c_lcd/__init__.py
i2c_lcd/i2c_lcd.py
i2c_lcd-0.1.0.dist-info/DESCRIPTION.rst
i2c_lcd-0.1.0.dist-info/METADATA
i2c_lcd-0.1.0.dist-info/RECORD
i2c_lcd-0.1.0.dist-info/WHEEL
i2c_lcd-0.1.0.dist-info/metadata.json
i2c_lcd-0.1.0.dist-info/top_level.txt
