Metadata-Version: 1.1
Name: i2c_lcd
Version: 0.1.0
Summary: I2C LCD interface in Python made for RPi.
Home-page: https://github.com/pwlandoll/i2c_lcd
Author: Peter Landoll
Author-email: pwlandoll@gmail.com
License: GNU General Public License v3
Keywords: i2c_lcd
Platform: UNKNOWN
Classifier: Development Status :: 2 - Pre-Alpha
Classifier: Intended Audience :: Developers
Classifier: License :: OSI Approved :: GNU General Public License v3 (GPLv3)
Classifier: Natural Language :: English
Classifier: Programming Language :: Python :: 2
Classifier: Programming Language :: Python :: 2.6
Classifier: Programming Language :: Python :: 2.7
Classifier: Programming Language :: Python :: 3
Classifier: Programming Language :: Python :: 3.3
Classifier: Programming Language :: Python :: 3.4
Classifier: Programming Language :: Python :: 3.5
